{
  "lexicon": 1,
  "id": "rsvp.atmo.space.invite.list",
  "defs": {
    "main": {
      "type": "query",
      "description": "List invites for a space. Owner only.",
      "parameters": {
        "type": "params",
        "required": [
          "spaceUri"
        ],
        "properties": {
          "spaceUri": {
            "type": "string",
            "format": "at-uri"
          },
          "includeRevoked": {
            "type": "boolean",
            "default": false
          }
        }
      },
      "output": {
        "encoding": "application/json",
        "schema": {
          "type": "object",
          "required": [
            "invites"
          ],
          "properties": {
            "invites": {
              "type": "array",
              "items": {
                "type": "ref",
                "ref": "rsvp.atmo.space.defs#inviteView"
              }
            }
          }
        }
      },
      "errors": [
        {
          "name": "NotFound"
        },
        {
          "name": "Forbidden"
        }
      ]
    }
  }
}
